LICENSE
pcurate.py
pcurate-0.1.6.dist-info/entry_points.txt
pcurate-0.1.6.dist-info/LICENSE
pcurate-0.1.6.dist-info/WHEEL
pcurate-0.1.6.dist-info/METADATA
pcurate-0.1.6.dist-info/RECORD
