Metadata-Version: 2.1
Name: pcurate
Version: 0.1.6
Summary: utility for curating Arch Linux software package lists
Home-page: https://github.com/thegibson/pcurate
License: MIT
Author: Scott Reed
Author-email: multivac@posteo.net
Requires-Python: >=3.9,<4.0
Classifier: License :: OSI Approved :: MIT License
Classifier: Programming Language :: Python :: 3
Classifier: Programming Language :: Python :: 3.10
Classifier: Programming Language :: Python :: 3.9
Requires-Dist: docopt (>=0.6.2,<0.7.0)
Project-URL: Repository, https://github.com/thegibson/pcurate
